padlet/__init__.py
padlet/data_models.py
padlet/wrapper.py
padlet_py-1.0.1.dist-info/LICENSE
padlet_py-1.0.1.dist-info/METADATA
padlet_py-1.0.1.dist-info/WHEEL
padlet_py-1.0.1.dist-info/top_level.txt
padlet_py-1.0.1.dist-info/RECORD
