Metadata-Version: 2.1
Name: padlet-py
Version: 1.0.1
Summary: A Padlet API wrapper written in python using async/await syntax
Author: Hypurrnating
License: MIT License
Project-URL: Repository, https://github.com/Hypurrnating/padlet-py
Keywords: padlet,padlet api,padlet wrapper
Classifier: Programming Language :: Python
Requires-Python: >=3.10
License-File: LICENSE
Requires-Dist: aiohttp
